hieropy/__init__.py
hieropy/edithistory.py
hieropy/editpreview.py
hieropy/edittree.py
hieropy/hieroparsing.py
hieropy/mdcconversion.py
hieropy/mdcnames.py
hieropy/mdcparsetab.py
hieropy/mdcstructure.py
hieropy/mdcsyntax.py
hieropy/menu.py
hieropy/ocr.py
hieropy/ocrdata.py
hieropy/options.py
hieropy/previewdrawing.py
hieropy/printables.py
hieropy/resconstants.py
hieropy/resconversion.py
hieropy/resparsetab.py
hieropy/resstructure.py
hieropy/ressyntax.py
hieropy/spatialparsing.py
hieropy/translit.py
hieropy/treedrawing.py
hieropy/uniconstants.py
hieropy/unieditor.py
hieropy/uninames.py
hieropy/uninormalization.py
hieropy/uniproperties.py
hieropy/unistats.py
hieropy/unistructure.py
hieropy/unisyntax.py
hieropy/unitransform.py
hieropy/resources/NewGardiner.ttf
hieropy/resources/broadnames.txt
hieropy/resources/circular.csv
hieropy/resources/edithelp.html
hieropy/resources/flattallnamesmdc.txt
hieropy/resources/flatwidenamesmdc.txt
hieropy/resources/insertions.json
hieropy/resources/keywordpoints.csv
hieropy/resources/legacy.csv
hieropy/resources/ligaturemdc.csv
hieropy/resources/ligatures.json
hieropy/resources/ligatureschemamdc.txt
hieropy/resources/lrsymmetric.csv
hieropy/resources/mnemonicname.csv
hieropy/resources/mnemonicnamemdc.csv
hieropy/resources/namecompositemdc.csv
hieropy/resources/namepoint.csv
hieropy/resources/namepointext.csv
hieropy/resources/namepointmdc.csv
hieropy/resources/namezonemdc.csv
hieropy/resources/narrownames.txt
hieropy/resources/ocrhstrokes.txt
hieropy/resources/ocromit.txt
hieropy/resources/ocrvstrokes.txt
hieropy/resources/pointinfo.csv
hieropy/resources/pointrotations.csv
hieropy/resources/tallnames.txt
hieropy/resources/tbsymmetric.csv
hieropy/resources/translitpoints.csv
hieropy-0.1.5.dist-info/licenses/LICENSE
hieropy-0.1.5.dist-info/METADATA
hieropy-0.1.5.dist-info/WHEEL
hieropy-0.1.5.dist-info/top_level.txt
hieropy-0.1.5.dist-info/RECORD
