Metadata-Version: 2.4
Name: hieropy
Version: 0.1.5
Summary: Processing of ancient Egyptian hieroglyphic text
Author-email: Mark-Jan Nederhof <markjan.nederhof@googlemail.com>
Project-URL: Source code, https://github.com/nederhof/hieropy
Requires-Python: >=3.9
License-File: LICENSE
Requires-Dist: numpy
Requires-Dist: Pillow
Requires-Dist: ply
Requires-Dist: pypdfium2==5.0.0
Requires-Dist: reportlab
Requires-Dist: rtree
Requires-Dist: scipy
Requires-Dist: shapely
Requires-Dist: svgwrite
Requires-Dist: tkhtmlview
Requires-Dist: tkinterweb
Dynamic: license-file
